[
  {
    "_id": 1,
    "company": "Company1",
    "drive_date": "2020-10-16",
    "students_attended": [
      1,
      2,
      3
    ]
  },
  {
    "_id": 2,
    "company": "Company2",
    "drive_date": "2020-10-17",
    "students_attended": [
      1,
      2,
      3
    ]
  },
  {
    "_id": 3,
    "company": "Company3",
    "drive_date": "2020-10-18",
    "students_attended": [
      1,
      2,
      3
    ]
  },
  {
    "_id": 4,
    "company": "Company4",
    "drive_date": "2020-10-19",
    "students_attended": [
      1,
      2,
      3
    ]
  },
  {
    "_id": 5,
    "company": "Company5",
    "drive_date": "2020-10-20",
    "students_attended": [
      1,
      2,
      3
    ]
  }
]